grpc_mcp_sdk/__init__.py
grpc_mcp_sdk/bridge.py
grpc_mcp_sdk/core.py
grpc_mcp_sdk-1.0.0.dist-info/licenses/LICENSE
grpc_mcp_sdk-1.0.0.dist-info/METADATA
grpc_mcp_sdk-1.0.0.dist-info/WHEEL
grpc_mcp_sdk-1.0.0.dist-info/entry_points.txt
grpc_mcp_sdk-1.0.0.dist-info/top_level.txt
grpc_mcp_sdk-1.0.0.dist-info/RECORD
