Metadata-Version: 2.4
Name: grpc-mcp-sdk
Version: 1.0.0
Summary: A modern Python framework for building high-performance MCP tools with gRPC
Author-email: gRPC MCP SDK Team <contact@grpc-mcp-sdk.com>
License-Expression: MIT
Project-URL: Homepage, https://github.com/grpc-mcp-sdk/grpc-mcp-sdk
Project-URL: Documentation, https://grpc-mcp-sdk.readthedocs.io/
Project-URL: Repository, https://github.com/grpc-mcp-sdk/grpc-mcp-sdk
Project-URL: Bug Tracker, https://github.com/grpc-mcp-sdk/grpc-mcp-sdk/issues
Keywords: grpc,mcp,model-context-protocol,ai,tools,api,microservices,rpc,protocol-buffers,streaming,performance,enterprise
Classifier: Development Status :: 4 - Beta
Classifier: Intended Audience :: Developers
Classifier: Operating System :: OS Independent
Classifier: Programming Language :: Python :: 3
Classifier: Programming Language :: Python :: 3.8
Classifier: Programming Language :: Python :: 3.9
Classifier: Programming Language :: Python :: 3.10
Classifier: Programming Language :: Python :: 3.11
Classifier: Programming Language :: Python :: 3.12
Classifier: Topic :: Software Development :: Libraries :: Python Modules
Classifier: Topic :: Internet :: WWW/HTTP :: HTTP Servers
Classifier: Topic :: System :: Distributed Computing
Requires-Python: >=3.8
License-File: LICENSE
Requires-Dist: grpcio>=1.60.0
Requires-Dist: grpcio-tools>=1.60.0
Requires-Dist: grpcio-health-checking>=1.60.0
Requires-Dist: grpcio-reflection>=1.60.0
Requires-Dist: protobuf>=4.25.0
Requires-Dist: aiohttp>=3.9.0
Requires-Dist: pydantic>=2.5.0
Requires-Dist: psutil>=5.9.0
Requires-Dist: aiofiles>=23.2.0
Provides-Extra: dev
Requires-Dist: pytest>=7.0.0; extra == "dev"
Requires-Dist: pytest-asyncio>=0.21.0; extra == "dev"
Requires-Dist: pytest-cov>=4.0.0; extra == "dev"
Requires-Dist: black>=23.0.0; extra == "dev"
Requires-Dist: isort>=5.12.0; extra == "dev"
Requires-Dist: flake8>=6.0.0; extra == "dev"
Requires-Dist: mypy>=1.5.0; extra == "dev"
Provides-Extra: docs
Requires-Dist: sphinx>=7.0.0; extra == "docs"
Requires-Dist: sphinx-rtd-theme>=1.3.0; extra == "docs"
Requires-Dist: sphinx-autodoc-typehints>=1.24.0; extra == "docs"
Provides-Extra: monitoring
Requires-Dist: prometheus-client>=0.17.0; extra == "monitoring"
Requires-Dist: psutil>=5.9.0; extra == "monitoring"
Provides-Extra: security
Requires-Dist: cryptography>=41.0.0; extra == "security"
Requires-Dist: pyjwt>=2.8.0; extra == "security"
Dynamic: license-file
